quotexpy/__init__.py
quotexpy/api.py
quotexpy/constants.py
quotexpy/exceptions/__init__.py
quotexpy/expiration.py
quotexpy/global_value.py
quotexpy/http/__init__.py
quotexpy/http/login.py
quotexpy/http/logout.py
quotexpy/http/navigator.py
quotexpy/http/qxbroker.py
quotexpy/http/user_agents.py
quotexpy/utils/__init__.py
quotexpy/utils/account_type.py
quotexpy/utils/operation_type.py
quotexpy/ws/__init__.py
quotexpy/ws/channels/base.py
quotexpy/ws/channels/candles.py
quotexpy/ws/channels/sell_option.py
quotexpy/ws/channels/ssid.py
quotexpy/ws/channels/trade.py
quotexpy/ws/client.py
quotexpy/ws/objects/base.py
quotexpy/ws/objects/candles.py
quotexpy/ws/objects/listinfodata.py
quotexpy/ws/objects/profile.py
quotexpy/ws/objects/timesync.py
quotexpy-1.40.6.dist-info/AUTHORS
quotexpy-1.40.6.dist-info/LICENSE
quotexpy-1.40.6.dist-info/METADATA
quotexpy-1.40.6.dist-info/WHEEL
quotexpy-1.40.6.dist-info/RECORD
