Metadata-Version: 2.1
Name: quotexpy
Version: 1.40.6
Summary: 📈 QuotexPy is a library to easily interact with qxbroker.
Home-page: https://github.com/SantiiRepair/quotexpy
License: LGPL-2.1
Keywords: quotex,quotexpy
Author: Santiago Ramirez
Author-email: santiirepair@gmail.com
Requires-Python: >=3.10,<3.13
Classifier: License :: OSI Approved
Classifier: Programming Language :: Python :: 3
Classifier: Programming Language :: Python :: 3.10
Classifier: Programming Language :: Python :: 3.11
Classifier: Programming Language :: Python :: 3.12
Requires-Dist: beautifulsoup4 (==4.11.2)
Requires-Dist: certifi (>=2022.12.7)
Requires-Dist: greenlet (>=2.0.1)
Requires-Dist: pyOpenSSL (>=23.1.1)
Requires-Dist: pytz (>=2023.3)
Requires-Dist: requests (>=2.31.0)
Requires-Dist: requests-toolbelt (>=1.0.0)
Requires-Dist: undetected-chromedriver (>=3.5.5)
Requires-Dist: urllib3 (>=2.0.5)
Requires-Dist: websocket-client (>=1.6.3)
Requires-Dist: websockets (>=11.0.3)
Project-URL: Repository, https://github.com/SantiiRepair/quotexpy
